{
  "version": 2,
  "extractor": "papercropper",
  "figures": [
    {
      "url": "assets/figures/arxiv/2606.06819v1/fig-001.webp",
      "caption": "",
      "page": 0,
      "index": 1,
      "width": 816,
      "height": 786,
      "label": "Figure"
    },
    {
      "url": "assets/figures/arxiv/2606.06819v1/fig-002.webp",
      "caption": "",
      "page": 0,
      "index": 2,
      "width": 1685,
      "height": 800,
      "label": "Figure"
    },
    {
      "url": "assets/figures/arxiv/2606.06819v1/fig-003.webp",
      "caption": "",
      "page": 0,
      "index": 3,
      "width": 1773,
      "height": 791,
      "label": "Figure"
    },
    {
      "url": "assets/figures/arxiv/2606.06819v1/fig-004.webp",
      "caption": "",
      "page": 0,
      "index": 4,
      "width": 1762,
      "height": 670,
      "label": "Figure"
    },
    {
      "url": "assets/figures/arxiv/2606.06819v1/fig-005.webp",
      "caption": "",
      "page": 0,
      "index": 5,
      "width": 1770,
      "height": 366,
      "label": "Figure"
    },
    {
      "url": "assets/figures/arxiv/2606.06819v1/fig-006.webp",
      "caption": "",
      "page": 0,
      "index": 6,
      "width": 1772,
      "height": 447,
      "label": "Figure"
    },
    {
      "url": "assets/figures/arxiv/2606.06819v1/fig-007.webp",
      "caption": "",
      "page": 0,
      "index": 7,
      "width": 1772,
      "height": 695,
      "label": "Figure"
    },
    {
      "url": "assets/figures/arxiv/2606.06819v1/fig-008.webp",
      "caption": "",
      "page": 0,
      "index": 8,
      "width": 703,
      "height": 404,
      "label": "Figure"
    },
    {
      "url": "assets/figures/arxiv/2606.06819v1/fig-009.webp",
      "caption": "",
      "page": 0,
      "index": 9,
      "width": 1676,
      "height": 873,
      "label": "Figure"
    },
    {
      "url": "assets/figures/arxiv/2606.06819v1/fig-010.webp",
      "caption": "",
      "page": 0,
      "index": 10,
      "width": 1632,
      "height": 836,
      "label": "Figure"
    },
    {
      "url": "assets/figures/arxiv/2606.06819v1/fig-011.webp",
      "caption": "",
      "page": 0,
      "index": 11,
      "width": 1733,
      "height": 1281,
      "label": "Figure"
    },
    {
      "url": "assets/figures/arxiv/2606.06819v1/fig-012.webp",
      "caption": "",
      "page": 0,
      "index": 12,
      "width": 1737,
      "height": 1263,
      "label": "Figure"
    }
  ]
}