{
  "version": 2,
  "extractor": "papercropper",
  "figures": [
    {
      "url": "assets/figures/openreview/openreview-neurips-2025-sujwddyspc/fig-001.webp",
      "caption": "",
      "page": 0,
      "index": 1,
      "width": 1434,
      "height": 869,
      "label": "Figure"
    },
    {
      "url": "assets/figures/openreview/openreview-neurips-2025-sujwddyspc/fig-002.webp",
      "caption": "",
      "page": 0,
      "index": 2,
      "width": 446,
      "height": 402,
      "label": "Figure"
    },
    {
      "url": "assets/figures/openreview/openreview-neurips-2025-sujwddyspc/fig-003.webp",
      "caption": "",
      "page": 0,
      "index": 3,
      "width": 234,
      "height": 395,
      "label": "Figure"
    },
    {
      "url": "assets/figures/openreview/openreview-neurips-2025-sujwddyspc/fig-004.webp",
      "caption": "",
      "page": 0,
      "index": 4,
      "width": 317,
      "height": 394,
      "label": "Figure"
    },
    {
      "url": "assets/figures/openreview/openreview-neurips-2025-sujwddyspc/fig-005.webp",
      "caption": "",
      "page": 0,
      "index": 5,
      "width": 213,
      "height": 374,
      "label": "Figure"
    },
    {
      "url": "assets/figures/openreview/openreview-neurips-2025-sujwddyspc/fig-006.webp",
      "caption": "",
      "page": 0,
      "index": 6,
      "width": 325,
      "height": 251,
      "label": "Figure"
    },
    {
      "url": "assets/figures/openreview/openreview-neurips-2025-sujwddyspc/fig-007.webp",
      "caption": "",
      "page": 0,
      "index": 7,
      "width": 372,
      "height": 284,
      "label": "Figure"
    },
    {
      "url": "assets/figures/openreview/openreview-neurips-2025-sujwddyspc/fig-008.webp",
      "caption": "",
      "page": 0,
      "index": 8,
      "width": 1366,
      "height": 882,
      "label": "Figure"
    },
    {
      "url": "assets/figures/openreview/openreview-neurips-2025-sujwddyspc/fig-009.webp",
      "caption": "",
      "page": 0,
      "index": 9,
      "width": 280,
      "height": 245,
      "label": "Figure"
    },
    {
      "url": "assets/figures/openreview/openreview-neurips-2025-sujwddyspc/fig-010.webp",
      "caption": "",
      "page": 0,
      "index": 10,
      "width": 189,
      "height": 246,
      "label": "Figure"
    },
    {
      "url": "assets/figures/openreview/openreview-neurips-2025-sujwddyspc/fig-011.webp",
      "caption": "",
      "page": 0,
      "index": 11,
      "width": 210,
      "height": 312,
      "label": "Figure"
    },
    {
      "url": "assets/figures/openreview/openreview-neurips-2025-sujwddyspc/fig-012.webp",
      "caption": "",
      "page": 0,
      "index": 12,
      "width": 258,
      "height": 289,
      "label": "Figure"
    },
    {
      "url": "assets/figures/openreview/openreview-neurips-2025-sujwddyspc/fig-013.webp",
      "caption": "",
      "page": 0,
      "index": 13,
      "width": 1586,
      "height": 2458,
      "label": "Figure"
    }
  ]
}