{
  "version": 2,
  "extractor": "papercropper",
  "tables": [
    {
      "url": "assets/tables/arxiv/2605.18202v1/table-001.webp",
      "caption": "",
      "page": 0,
      "index": 1,
      "width": 1343,
      "height": 317,
      "label": "Table"
    },
    {
      "url": "assets/tables/arxiv/2605.18202v1/table-002.webp",
      "caption": "",
      "page": 0,
      "index": 2,
      "width": 1212,
      "height": 450,
      "label": "Table"
    },
    {
      "url": "assets/tables/arxiv/2605.18202v1/table-003.webp",
      "caption": "",
      "page": 0,
      "index": 3,
      "width": 1416,
      "height": 328,
      "label": "Table"
    },
    {
      "url": "assets/tables/arxiv/2605.18202v1/table-004.webp",
      "caption": "",
      "page": 0,
      "index": 4,
      "width": 1263,
      "height": 377,
      "label": "Table"
    },
    {
      "url": "assets/tables/arxiv/2605.18202v1/table-005.webp",
      "caption": "",
      "page": 0,
      "index": 5,
      "width": 1454,
      "height": 269,
      "label": "Table"
    },
    {
      "url": "assets/tables/arxiv/2605.18202v1/table-006.webp",
      "caption": "",
      "page": 0,
      "index": 6,
      "width": 1307,
      "height": 341,
      "label": "Table"
    },
    {
      "url": "assets/tables/arxiv/2605.18202v1/table-007.webp",
      "caption": "",
      "page": 0,
      "index": 7,
      "width": 1306,
      "height": 342,
      "label": "Table"
    },
    {
      "url": "assets/tables/arxiv/2605.18202v1/table-008.webp",
      "caption": "",
      "page": 0,
      "index": 8,
      "width": 1344,
      "height": 400,
      "label": "Table"
    },
    {
      "url": "assets/tables/arxiv/2605.18202v1/table-009.webp",
      "caption": "",
      "page": 0,
      "index": 9,
      "width": 1361,
      "height": 338,
      "label": "Table"
    },
    {
      "url": "assets/tables/arxiv/2605.18202v1/table-010.webp",
      "caption": "",
      "page": 0,
      "index": 10,
      "width": 1349,
      "height": 337,
      "label": "Table"
    },
    {
      "url": "assets/tables/arxiv/2605.18202v1/table-011.webp",
      "caption": "",
      "page": 0,
      "index": 11,
      "width": 1349,
      "height": 339,
      "label": "Table"
    },
    {
      "url": "assets/tables/arxiv/2605.18202v1/table-012.webp",
      "caption": "",
      "page": 0,
      "index": 12,
      "width": 1347,
      "height": 339,
      "label": "Table"
    },
    {
      "url": "assets/tables/arxiv/2605.18202v1/table-013.webp",
      "caption": "",
      "page": 0,
      "index": 13,
      "width": 1307,
      "height": 340,
      "label": "Table"
    },
    {
      "url": "assets/tables/arxiv/2605.18202v1/table-014.webp",
      "caption": "",
      "page": 0,
      "index": 14,
      "width": 1306,
      "height": 338,
      "label": "Table"
    },
    {
      "url": "assets/tables/arxiv/2605.18202v1/table-015.webp",
      "caption": "",
      "page": 0,
      "index": 15,
      "width": 1317,
      "height": 337,
      "label": "Table"
    },
    {
      "url": "assets/tables/arxiv/2605.18202v1/table-016.webp",
      "caption": "",
      "page": 0,
      "index": 16,
      "width": 1319,
      "height": 339,
      "label": "Table"
    },
    {
      "url": "assets/tables/arxiv/2605.18202v1/table-017.webp",
      "caption": "",
      "page": 0,
      "index": 17,
      "width": 1331,
      "height": 338,
      "label": "Table"
    },
    {
      "url": "assets/tables/arxiv/2605.18202v1/table-018.webp",
      "caption": "",
      "page": 0,
      "index": 18,
      "width": 1331,
      "height": 340,
      "label": "Table"
    },
    {
      "url": "assets/tables/arxiv/2605.18202v1/table-019.webp",
      "caption": "",
      "page": 0,
      "index": 19,
      "width": 1349,
      "height": 338,
      "label": "Table"
    },
    {
      "url": "assets/tables/arxiv/2605.18202v1/table-020.webp",
      "caption": "",
      "page": 0,
      "index": 20,
      "width": 1348,
      "height": 337,
      "label": "Table"
    },
    {
      "url": "assets/tables/arxiv/2605.18202v1/table-021.webp",
      "caption": "",
      "page": 0,
      "index": 21,
      "width": 1335,
      "height": 338,
      "label": "Table"
    },
    {
      "url": "assets/tables/arxiv/2605.18202v1/table-022.webp",
      "caption": "",
      "page": 0,
      "index": 22,
      "width": 1332,
      "height": 338,
      "label": "Table"
    },
    {
      "url": "assets/tables/arxiv/2605.18202v1/table-023.webp",
      "caption": "",
      "page": 0,
      "index": 23,
      "width": 1346,
      "height": 340,
      "label": "Table"
    },
    {
      "url": "assets/tables/arxiv/2605.18202v1/table-024.webp",
      "caption": "",
      "page": 0,
      "index": 24,
      "width": 1334,
      "height": 338,
      "label": "Table"
    },
    {
      "url": "assets/tables/arxiv/2605.18202v1/table-025.webp",
      "caption": "",
      "page": 0,
      "index": 25,
      "width": 1347,
      "height": 337,
      "label": "Table"
    },
    {
      "url": "assets/tables/arxiv/2605.18202v1/table-026.webp",
      "caption": "",
      "page": 0,
      "index": 26,
      "width": 1348,
      "height": 339,
      "label": "Table"
    },
    {
      "url": "assets/tables/arxiv/2605.18202v1/table-027.webp",
      "caption": "",
      "page": 0,
      "index": 27,
      "width": 1319,
      "height": 338,
      "label": "Table"
    },
    {
      "url": "assets/tables/arxiv/2605.18202v1/table-028.webp",
      "caption": "",
      "page": 0,
      "index": 28,
      "width": 1330,
      "height": 340,
      "label": "Table"
    },
    {
      "url": "assets/tables/arxiv/2605.18202v1/table-029.webp",
      "caption": "",
      "page": 0,
      "index": 29,
      "width": 1334,
      "height": 340,
      "label": "Table"
    },
    {
      "url": "assets/tables/arxiv/2605.18202v1/table-030.webp",
      "caption": "",
      "page": 0,
      "index": 30,
      "width": 1332,
      "height": 339,
      "label": "Table"
    },
    {
      "url": "assets/tables/arxiv/2605.18202v1/table-031.webp",
      "caption": "",
      "page": 0,
      "index": 31,
      "width": 1284,
      "height": 213,
      "label": "Table"
    },
    {
      "url": "assets/tables/arxiv/2605.18202v1/table-032.webp",
      "caption": "",
      "page": 0,
      "index": 32,
      "width": 1230,
      "height": 1174,
      "label": "Table"
    },
    {
      "url": "assets/tables/arxiv/2605.18202v1/table-033.webp",
      "caption": "",
      "page": 0,
      "index": 33,
      "width": 1219,
      "height": 1171,
      "label": "Table"
    },
    {
      "url": "assets/tables/arxiv/2605.18202v1/table-034.webp",
      "caption": "",
      "page": 0,
      "index": 34,
      "width": 533,
      "height": 326,
      "label": "Table"
    }
  ]
}